README.md
setup.py
taoassets_taopy.egg-info/PKG-INFO
taoassets_taopy.egg-info/SOURCES.txt
taoassets_taopy.egg-info/dependency_links.txt
taoassets_taopy.egg-info/requires.txt
taoassets_taopy.egg-info/top_level.txt
taopy/__init__.py
taopy/constants.py
taopy/lib/__init__.py
taopy/lib/base58.py
taopy/lib/bech32.py
taopy/lib/codecs.py
taopy/lib/opcodes.py
taopy/lib/parsing.py
taopy/lib/types.py
taopy/structs/__init__.py
taopy/structs/address.py
taopy/structs/block.py
taopy/structs/crypto.py
taopy/structs/hd.py
taopy/structs/script.py
taopy/structs/sig.py
taopy/structs/transaction.py
tests/__init__.py
tests/integration.py
tests/regtest.py
tests/unit.py