Metadata-Version: 2.1
Name: taoassets-taopy
Version: 0.6.8
Summary: A Python3 SegWit-compliant library which provides tools to handle Tao data structures in a simple fashion.
Home-page: https://github.com/taoblockchain/taopy
Author: chainside srl, PeerAssets & TaoAssets development team
License: UNKNOWN
Keywords: tao,blockchain,bitcoin,peercoin,taoassets
Platform: UNKNOWN
Requires-Python: >=3
Provides-Extra: develop
